socketpulse/__init__.py
socketpulse/__main__.py
socketpulse/connection.py
socketpulse/handlers.py
socketpulse/openapi.py
socketpulse/server.py
socketpulse/tags.py
socketpulse/types.py
socketpulse/resources/favicon.ico
socketpulse/resources/swagger.html
socketpulse/resources/playground/panels.js
socketpulse/resources/playground/playground.html
socketpulse/resources/playground/playground.js
socketpulse/samples/__init__.py
socketpulse/samples/file_sample.py
socketpulse/samples/sample.py
socketpulse-1.1.0.dist-info/LICENSE
socketpulse-1.1.0.dist-info/METADATA
socketpulse-1.1.0.dist-info/WHEEL
socketpulse-1.1.0.dist-info/top_level.txt
socketpulse-1.1.0.dist-info/RECORD
