Metadata-Version: 2.1
Name: socketpulse
Version: 1.1.0
Summary: A simple Python library for creating web servers and APIs using sockets, supporting openapi and swagger.
Author-email: Caleb <jonathancaleb230@gmail.com>
License: GNU GENERAL PUBLIC LICENSE
Project-URL: Homepage, https://github.com/modularizer/socketpulse
Classifier: Programming Language :: Python :: 3.12
Classifier: Operating System :: OS Independent
Requires-Python: >=3.10
License-File: LICENSE
